mcts_simple/__init__.py
mcts_simple/mcts/game.py
mcts_simple/mcts/mcts.py
mcts_simple/mcts/open_loop_mcts.py
mcts_simple/mcts/open_loop_uct.py
mcts_simple/mcts/uct.py
mcts_simple-1.1.0.dist-info/licenses/LICENSE
mcts_simple-1.1.0.dist-info/METADATA
mcts_simple-1.1.0.dist-info/WHEEL
mcts_simple-1.1.0.dist-info/top_level.txt
mcts_simple-1.1.0.dist-info/RECORD
