Metadata-Version: 2.4
Name: mcts-simple
Version: 1.1.0
Summary: mcts-simple is a Python3 library that implements Monte Carlo Tree Search and its variants to solve a host of problems, most commonly for reinforcement learning.
Home-page: https://github.com/DenseLance/mcts-simple
Author: Lance Chin
Author-email: denselance@gmail.com
License: MIT
Project-URL: Bug Tracker, https://github.com/DenseLance/mcts-simple/issues
Classifier: Intended Audience :: Science/Research
Classifier: License :: OSI Approved :: MIT License
Classifier: Programming Language :: Python
Classifier: Programming Language :: Python :: 3
Classifier: Programming Language :: Python :: 3.8
Classifier: Programming Language :: Python :: 3.9
Classifier: Programming Language :: Python :: 3.10
Classifier: Programming Language :: Python :: 3.11
Classifier: Programming Language :: Python :: 3.12
Classifier: Programming Language :: Python :: 3.13
Requires-Python: >=3.8.0
License-File: LICENSE
Requires-Dist: tqdm
Requires-Dist: msgpack
Dynamic: author
Dynamic: author-email
Dynamic: classifier
Dynamic: description
Dynamic: description-content-type
Dynamic: home-page
Dynamic: license
Dynamic: license-file
Dynamic: project-url
Dynamic: requires-dist
Dynamic: requires-python
Dynamic: summary
